graze/__init__.py
graze/base.py
graze/migration_tools.py
graze/util.py
graze-0.1.32.dist-info/LICENSE
graze-0.1.32.dist-info/METADATA
graze-0.1.32.dist-info/WHEEL
graze-0.1.32.dist-info/top_level.txt
graze-0.1.32.dist-info/RECORD
