Metadata-Version: 2.1
Name: graze
Version: 0.1.32
Summary: Cache (a tiny part of) the internet
Home-page: https://github.com/thorwhalen/graze
Author: Thor Whalen
License: mit
Platform: any
License-File: LICENSE
Requires-Dist: dol
Requires-Dist: requests
